lextok/__init__.py
lextok/main.py
lextok/names.py
lextok/pretest.py
lextok/rules/__init__.py
lextok/rules/_pattern.py
lextok/rules/abbreviations.py
lextok/rules/attribute_ruler.py
lextok/rules/custom_tokenizer.py
lextok/rules/rule_basic.py
lextok/rules/rule_casenames.py
lextok/rules/rule_citeables.py
lextok/rules/rule_courtnames.py
lextok/rules/rule_date.py
lextok/rules/rule_docketnums.py
lextok/rules/rule_generics_irrs.py
lextok/rules/rule_juridicals.py
lextok/rules/rule_provisionnums.py
lextok/rules/rule_statutenames.py
lextok/rules/rule_statutenums.py
lextok/utils.py
lextok-0.0.27.dist-info/METADATA
lextok-0.0.27.dist-info/WHEEL
lextok-0.0.27.dist-info/RECORD
