Metadata-Version: 2.1
Name: lextok
Version: 0.0.27
Summary: Legalese tokenization
Home-page: https://mv3.dev
Author: Marcelino G. Veloso III
Author-email: contact@mv3.dev
Requires-Python: >=3.11,<4.0
Classifier: Development Status :: 4 - Beta
Classifier: Framework :: Pytest
Classifier: Programming Language :: Python :: 3
Classifier: Programming Language :: Python :: 3.11
Classifier: Programming Language :: Python :: 3.12
Classifier: Typing :: Typed
Requires-Dist: inflect (>=7.0.0,<8.0.0)
Requires-Dist: jsonlines (>=4.0.0,<5.0.0)
Requires-Dist: python-slugify (>=8.0.1,<9.0.0)
Requires-Dist: roman (>=4.1,<5.0)
Requires-Dist: spacy[apple] (>=3.7.2,<4.0.0)
Project-URL: Documentation, https://justmars.github.io/lextok
Project-URL: Repository, https://github.com/justmars/lextok
